{"name":"JavaFX","classpathEntries":[{"kind":"binary","path":"C:\\Program Files\\AdoptOpenJDK\\jdk-11.0.4+11\\lib\\jrt-fs.jar","sourceContainerUrl":"file:/C:/Program%20Files/AdoptOpenJDK/jdk-11.0.4+11/lib/src.zip","javadocContainerUrl":"https://docs.oracle.com/javase/11/docs/api/","isSystem":true,"isOwn":false,"isTest":false,"isJavaContent":false},{"kind":"binary","path":"C:\\Users\\moimah\\.m2\\repository\\org\\openjfx\\javafx-controls\\11.0.1\\javafx-controls-11.0.1.jar","sourceContainerUrl":"file:/C:/Users/moimah/.m2/repository/org/openjfx/javafx-controls/11.0.1/javafx-controls-11.0.1-sources.jar","javadocContainerUrl":"file:/C:/Users/moimah/.m2/repository/org/openjfx/javafx-controls/11.0.1/javafx-controls-11.0.1-javadoc.jar","isSystem":false,"isOwn":false,"isTest":false,"isJavaContent":false},{"kind":"binary","path":"C:\\Users\\moimah\\.m2\\repository\\org\\openjfx\\javafx-controls\\11.0.1\\javafx-controls-11.0.1-win.jar","sourceContainerUrl":"file:/C:/Users/moimah/.m2/repository/org/openjfx/javafx-controls/11.0.1/javafx-controls-11.0.1-sources.jar","javadocContainerUrl":"file:/C:/Users/moimah/.m2/repository/org/openjfx/javafx-controls/11.0.1/javafx-controls-11.0.1-javadoc.jar","isSystem":false,"isOwn":false,"isTest":false,"isJavaContent":false},{"kind":"binary","path":"C:\\Users\\moimah\\.m2\\repository\\org\\openjfx\\javafx-graphics\\11.0.1\\javafx-graphics-11.0.1.jar","sourceContainerUrl":"file:/C:/Users/moimah/.m2/repository/org/openjfx/javafx-graphics/11.0.1/javafx-graphics-11.0.1-sources.jar","javadocContainerUrl":"file:/C:/Users/moimah/.m2/repository/org/openjfx/javafx-graphics/11.0.1/javafx-graphics-11.0.1-javadoc.jar","isSystem":false,"isOwn":false,"isTest":false,"isJavaContent":false},{"kind":"binary","path":"C:\\Users\\moimah\\.m2\\repository\\org\\openjfx\\javafx-graphics\\11.0.1\\javafx-graphics-11.0.1-win.jar","sourceContainerUrl":"file:/C:/Users/moimah/.m2/repository/org/openjfx/javafx-graphics/11.0.1/javafx-graphics-11.0.1-sources.jar","javadocContainerUrl":"file:/C:/Users/moimah/.m2/repository/org/openjfx/javafx-graphics/11.0.1/javafx-graphics-11.0.1-javadoc.jar","isSystem":false,"isOwn":false,"isTest":false,"isJavaContent":false},{"kind":"binary","path":"C:\\Users\\moimah\\.m2\\repository\\org\\openjfx\\javafx-base\\11.0.1\\javafx-base-11.0.1.jar","sourceContainerUrl":"file:/C:/Users/moimah/.m2/repository/org/openjfx/javafx-base/11.0.1/javafx-base-11.0.1-sources.jar","javadocContainerUrl":"file:/C:/Users/moimah/.m2/repository/org/openjfx/javafx-base/11.0.1/javafx-base-11.0.1-javadoc.jar","isSystem":false,"isOwn":false,"isTest":false,"isJavaContent":false},{"kind":"binary","path":"C:\\Users\\moimah\\.m2\\repository\\org\\openjfx\\javafx-base\\11.0.1\\javafx-base-11.0.1-win.jar","sourceContainerUrl":"file:/C:/Users/moimah/.m2/repository/org/openjfx/javafx-base/11.0.1/javafx-base-11.0.1-sources.jar","javadocContainerUrl":"file:/C:/Users/moimah/.m2/repository/org/openjfx/javafx-base/11.0.1/javafx-base-11.0.1-javadoc.jar","isSystem":false,"isOwn":false,"isTest":false,"isJavaContent":false},{"kind":"binary","path":"C:\\Users\\moimah\\.m2\\repository\\org\\openjfx\\javafx-fxml\\11.0.1\\javafx-fxml-11.0.1.jar","sourceContainerUrl":"file:/C:/Users/moimah/.m2/repository/org/openjfx/javafx-fxml/11.0.1/javafx-fxml-11.0.1-sources.jar","javadocContainerUrl":"file:/C:/Users/moimah/.m2/repository/org/openjfx/javafx-fxml/11.0.1/javafx-fxml-11.0.1-javadoc.jar","isSystem":false,"isOwn":false,"isTest":false,"isJavaContent":false},{"kind":"binary","path":"C:\\Users\\moimah\\.m2\\repository\\org\\openjfx\\javafx-fxml\\11.0.1\\javafx-fxml-11.0.1-win.jar","sourceContainerUrl":"file:/C:/Users/moimah/.m2/repository/org/openjfx/javafx-fxml/11.0.1/javafx-fxml-11.0.1-sources.jar","javadocContainerUrl":"file:/C:/Users/moimah/.m2/repository/org/openjfx/javafx-fxml/11.0.1/javafx-fxml-11.0.1-javadoc.jar","isSystem":false,"isOwn":false,"isTest":false,"isJavaContent":false},{"kind":"source","path":"W:\\Java\\DAD\\DAD_02\\JavaFXProjectTemplate\\src\\main\\java","outputFolder":"W:\\Java\\DAD\\DAD_02\\JavaFXProjectTemplate\\target\\classes","javadocContainerUrl":"file:/W:/Java/DAD/DAD_02/JavaFXProjectTemplate/target/site/apidocs","isSystem":false,"isOwn":true,"isTest":false,"isJavaContent":true},{"kind":"source","path":"W:\\Java\\DAD\\DAD_02\\JavaFXProjectTemplate\\src\\main\\resources","outputFolder":"W:\\Java\\DAD\\DAD_02\\JavaFXProjectTemplate\\target\\classes","isSystem":false,"isOwn":true,"isTest":false,"isJavaContent":false},{"kind":"source","path":"W:\\Java\\DAD\\DAD_02\\JavaFXProjectTemplate\\src\\test\\resources","outputFolder":"W:\\Java\\DAD\\DAD_02\\JavaFXProjectTemplate\\target\\test-classes","isSystem":false,"isOwn":true,"isTest":true,"isJavaContent":false},{"kind":"source","path":"W:\\Java\\DAD\\DAD_02\\JavaFXProjectTemplate\\src\\test\\java","outputFolder":"W:\\Java\\DAD\\DAD_02\\JavaFXProjectTemplate\\target\\test-classes","javadocContainerUrl":"file:/W:/Java/DAD/DAD_02/JavaFXProjectTemplate/target/site/apidocs","isSystem":false,"isOwn":true,"isTest":false,"isJavaContent":false}]}